{
    "general": {
        "grid": {
            "x": 1,
            "y": 1
        },
        "from": "2019-12-31T23:00:00.000Z",
        "to": "2020-12-31T23:00:00.000Z"
    },
    "parking_lots": [
        {
            "id": "a",
            "capacity": 20,
            "x": 0,
            "y": 0
        }
    ],
    "profiles": [
        {
            "id": 1,
            "start": {
                "type": "gauss",
                "mean": 8,
                "std_dev": 0.5
            },
            "duration": {
                "type": "gauss",
                "mean": 8,
                "std_dev": 2
            },
            "target": {
                "type": "point",
                "min_x": 0,
                "min_y": 0
            },
            "count": {
                "type": "gauss",
                "mean": 8,
                "std_dev": 1
            }
        },
        {
            "id": 2,
            "start": {
                "type": "uniform",
                "min": 0,
                "max": 24
            },
            "duration": {
                "type": "gauss",
                "mean": 2,
                "std_dev": 1
            },
            "target": {
                "type": "point",
                "min_x": 0,
                "min_y": 0
            },
            "count": {
                "type": "gauss",
                "mean": 20,
                "std_dev": 3
            }
        },
        {
            "id": 3,
            "start": {
                "type": "uniform",
                "min": 0,
                "max": 24
            },
            "duration": {
                "type": "gauss",
                "mean": 6,
                "std_dev": 2
            },
            "target": {
                "type": "uniform",
                "min_x": 0,
                "max_x": 0,
                "min_y": 0,
                "max_y": 0
            },
            "count": {
                "type": "gauss",
                "mean": 40,
                "std_dev": 2
            }
        }
    ],
    "disruptions": [
        {
            "tag": "type-e",
            "from": "2020-02-02T03:03:43.316Z",
            "to": "2020-02-02T07:51:04.416Z",
            "x": 0,
            "y": 0
        },
        {
            "tag": "type-e",
            "from": "2020-03-05T14:41:23.063Z",
            "to": "2020-03-05T17:46:50.847Z",
            "x": 0,
            "y": 0
        },
        {
            "tag": "type-e",
            "from": "2020-04-07T08:21:29.106Z",
            "to": "2020-04-07T13:27:42.898Z",
            "x": 0,
            "y": 0
        },
        {
            "tag": "type-e",
            "from": "2020-05-11T09:01:30.859Z",
            "to": "2020-05-11T13:01:08.520Z",
            "x": 0,
            "y": 0
        },
        {
            "tag": "type-e",
            "from": "2020-06-15T06:17:13.106Z",
            "to": "2020-06-15T10:51:39.767Z",
            "x": 0,
            "y": 0
        },
        {
            "tag": "type-e",
            "from": "2020-07-19T21:29:25.805Z",
            "to": "2020-07-20T00:46:49.502Z",
            "x": 0,
            "y": 0
        },
        {
            "tag": "type-e",
            "from": "2020-08-21T11:53:50.609Z",
            "to": "2020-08-21T17:52:04.379Z",
            "x": 0,
            "y": 0
        },
        {
            "tag": "type-e",
            "from": "2020-09-24T17:12:45.115Z",
            "to": "2020-09-24T21:46:37.055Z",
            "x": 0,
            "y": 0
        },
        {
            "tag": "type-e",
            "from": "2020-10-27T20:22:14.786Z",
            "to": "2020-10-28T01:38:45.836Z",
            "x": 0,
            "y": 0
        },
        {
            "tag": "type-e",
            "from": "2020-11-30T19:32:15.819Z",
            "to": "2020-11-30T22:49:43.101Z",
            "x": 0,
            "y": 0
        }
    ]
}