{
    "services": [
        {
            "name": "serviceA",
            "error_rate": 0.001,
            "durations": [
                {
                    "type": "gauss",
                    "mean": 1000,
                    "std_dev": 50,
                    "min_ts": "2016-12-30T23:00:00.000Z",
                    "max_ts": "2018-01-01T23:00:00.000Z"
                }
            ],
            "deps": []
        }
    ],
    "service_calls": [
        {
            "service": "serviceA",
            "type": "const",
            "active": [
                0,
                12
            ],
            "weekend": false,
            "low": 5000,
            "high": 5000,
            "noise": 0.05
        }
    ],
    "servers": [
        {
            "name": "srvr1",
            "services": [
                "serviceA"
            ]
        }
    ],
    "general": {
        "from": "2017-01-01T00:00:00",
        "to": "2018-01-01T00:00:00"
    },
    "disruptions": [
        {
            "tag": "type3",
            "from": "2017-01-31T11:37:42.185Z",
            "to": "2017-02-04T20:41:14.650Z",
            "services": [
                "serviceA"
            ],
            "disruption": {
                "type": "linear",
                "min": 1100,
                "max": 10000,
                "std_dev": 20,
                "min_ts": "2017-01-31T11:37:42.185Z",
                "max_ts": "2017-02-04T20:41:14.650Z"
            }
        },
        {
            "tag": "type3",
            "from": "2017-03-14T15:48:40.934Z",
            "to": "2017-03-17T11:07:32.179Z",
            "services": [
                "serviceA"
            ],
            "disruption": {
                "type": "linear",
                "min": 1100,
                "max": 10000,
                "std_dev": 20,
                "min_ts": "2017-03-14T15:48:40.934Z",
                "max_ts": "2017-03-17T11:07:32.179Z"
            }
        },
        {
            "tag": "type3",
            "from": "2017-04-25T22:20:41.886Z",
            "to": "2017-04-30T21:08:12.178Z",
            "services": [
                "serviceA"
            ],
            "disruption": {
                "type": "linear",
                "min": 1100,
                "max": 10000,
                "std_dev": 20,
                "min_ts": "2017-04-25T22:20:41.886Z",
                "max_ts": "2017-04-30T21:08:12.178Z"
            }
        },
        {
            "tag": "type3",
            "from": "2017-06-07T15:34:42.714Z",
            "to": "2017-06-11T10:14:31.854Z",
            "services": [
                "serviceA"
            ],
            "disruption": {
                "type": "linear",
                "min": 1100,
                "max": 10000,
                "std_dev": 20,
                "min_ts": "2017-06-07T15:34:42.714Z",
                "max_ts": "2017-06-11T10:14:31.854Z"
            }
        },
        {
            "tag": "type3",
            "from": "2017-07-19T03:23:46.926Z",
            "to": "2017-07-22T08:29:56.238Z",
            "services": [
                "serviceA"
            ],
            "disruption": {
                "type": "linear",
                "min": 1100,
                "max": 10000,
                "std_dev": 20,
                "min_ts": "2017-07-19T03:23:46.926Z",
                "max_ts": "2017-07-22T08:29:56.238Z"
            }
        },
        {
            "tag": "type3",
            "from": "2017-08-31T04:28:14.858Z",
            "to": "2017-09-03T08:06:41.477Z",
            "services": [
                "serviceA"
            ],
            "disruption": {
                "type": "linear",
                "min": 1100,
                "max": 10000,
                "std_dev": 20,
                "min_ts": "2017-08-31T04:28:14.858Z",
                "max_ts": "2017-09-03T08:06:41.477Z"
            }
        },
        {
            "tag": "type3",
            "from": "2017-10-10T08:22:57.357Z",
            "to": "2017-10-14T11:04:39.500Z",
            "services": [
                "serviceA"
            ],
            "disruption": {
                "type": "linear",
                "min": 1100,
                "max": 10000,
                "std_dev": 20,
                "min_ts": "2017-10-10T08:22:57.357Z",
                "max_ts": "2017-10-14T11:04:39.500Z"
            }
        },
        {
            "tag": "type3",
            "from": "2017-11-22T22:34:55.348Z",
            "to": "2017-11-27T03:25:04.926Z",
            "services": [
                "serviceA"
            ],
            "disruption": {
                "type": "linear",
                "min": 1100,
                "max": 10000,
                "std_dev": 20,
                "min_ts": "2017-11-22T22:34:55.348Z",
                "max_ts": "2017-11-27T03:25:04.926Z"
            }
        }
    ]
}